Workbook

Sheet Consignas

Sheet Ejercicio 1
A1: N° de 5 dígitos | C1: Gastos de transporte | D1: Salario | F1: Fecha | H1: Edad
A2: 3 | C2: 500 | D2: 4000 | F2: 45874 | H2: 18

Sheet Ejercicio 2
A1: ='Sucursal 1'!$D$5 -> 24600
A2: ='Sucursal 2'!$D$5 -> 21200
A3: ='Sucursal 3'!$D$5 -> 24900
B4: ='Sucursal 1'!$D$5 -> 24600
B5: ='Sucursal 2'!$D$5 -> 21200
B6: ='Sucursal 3'!$D$5 -> 24900
A10: Suma de sucursales
A14: =SUM(A1:A3) -> 70700

Sheet Sucursal 1
A1: Producto | B1: Cantidad | C1: Precio Unitario | D1: Total
A2: Lápices | B2: 100 | C2: 50 | D2: =Tabla1[[#This Row],[Precio Unitario]]*Tabla1[[#This Row],[Cantidad]] -> 5000
A3: Cuadernos | B3: 80 | C3: 120 | D3: =Tabla1[[#This Row],[Precio Unitario]]*Tabla1[[#This Row],[Cantidad]] -> 9600
A4: Carpetas | B4: 50 | C4: 200 | D4: =Tabla1[[#This Row],[Precio Unitario]]*Tabla1[[#This Row],[Cantidad]] -> 10000
A5: Total ventas | D5: =SUM(D2:D4) -> 24600

Sheet Sucursal 2
A1: Producto | B1: Cantidad | C1: Precio Unitario | D1: Total
A2: Lápices | B2: 120 | C2: 50 | D2: =Tabla2[[#This Row],[Precio Unitario]]*Tabla2[[#This Row],[Cantidad]] -> 6000
A3: Cuadernos | B3: 60 | C3: 120 | D3: =Tabla2[[#This Row],[Precio Unitario]]*Tabla2[[#This Row],[Cantidad]] -> 7200
A4: Carpetas | B4: 40 | C4: 200 | D4: =Tabla2[[#This Row],[Precio Unitario]]*Tabla2[[#This Row],[Cantidad]] -> 8000
A5: Total ventas | D5: =SUM(D2:D4) -> 21200

Sheet Sucursal 3
A1: Producto | B1: Cantidad | C1: Precio Unitario | D1: Total
A2: Lápices | B2: 90 | C2: 50 | D2: =Tabla3[[#This Row],[Precio Unitario]]*Tabla3[[#This Row],[Cantidad]] -> 4500
A3: Cuadernos | B3: 70 | C3: 120 | D3: =Tabla3[[#This Row],[Precio Unitario]]*Tabla3[[#This Row],[Cantidad]] -> 8400
A4: Carpetas | B4: 60 | C4: 200 | D4: =Tabla3[[#This Row],[Precio Unitario]]*Tabla3[[#This Row],[Cantidad]] -> 12000
A5: Total ventas | D5: =SUM(D2:D4) -> 24900

Sheet Resumen - Notas
A1: Alumno | C1: Nota
B2: Ejercicios - Unidad 2 | C2: =Biología!$B$2 -> 10
B3: Ejercicios - Unidad 2 | C3: =Historia!$B$2 -> 9
B4: Ejercicios - Unidad 2 | C4: =Matemática!$B$2 -> 8
A5: Ana | C5: =AVERAGE(C2:C4) -> 9
B6: Ejercicios - Unidad 2 | C6: =Biología!$B$3 -> 3
B7: Ejercicios - Unidad 2 | C7: =Historia!$B$3 -> 4
B8: Ejercicios - Unidad 2 | C8: =Matemática!$B$3 -> 6
A9: Bruno | C9: =ROUNDDOWN(AVERAGE(C6:C8),2) -> 4.33
B10: Ejercicios - Unidad 2 | C10: =Biología!$B$4 -> 7
B11: Ejercicios - Unidad 2 | C11: =Historia!$B$4 -> 10
B12: Ejercicios - Unidad 2 | C12: =Matemática!$B$4 -> 9
A13: Carla | C13: =ROUNDDOWN(AVERAGE(C10:C12),2) -> 8.66

Sheet Matemática
A1: Alumno | B1: Nota
A2: Ana | B2: 8
A3: Bruno | B3: 6
A4: Carla | B4: 9

Sheet Historia
A1: Alumno | B1: Nota
A2: Ana | B2: 9
A3: Bruno | B3: 4
A4: Carla | B4: 10

Sheet Biología
A1: Alumno | B1: Nota
A2: Ana | B2: 10
A3: Bruno | B3: 3
A4: Carla | B4: 7

Sheet Resumen anual - Ventas
A1: Producto | C1: Ventas Totales
B2: Ejercicios - Unidad 2 | C2: =Enero!$B$2 -> 5000
B3: Ejercicios - Unidad 2 | C3: =Febrero!$B$2 -> 6000
A4: Lápices | C4: =SUM(C2:C3) -> 11000
B5: Ejercicios - Unidad 2 | C5: =Enero!$B$3 -> 9600
B6: Ejercicios - Unidad 2 | C6: =Febrero!$B$3 -> 8700
A7: Cuadernos | C7: =SUM(C5:C6) -> 18300
B8: Ejercicios - Unidad 2 | C8: =Enero!$B$4 -> 10000
B9: Ejercicios - Unidad 2 | C9: =Febrero!$B$4 -> 12000
A10: Carpetas | C10: =SUM(C8:C9) -> 22000

Sheet Enero
A1: Producto | B1: Ventas
A2: Lápices | B2: 5000
A3: Cuadernos | B3: 9600
A4: Carpetas | B4: 10000

Sheet Febrero
A1: Producto | B1: Ventas
A2: Lápices | B2: 6000
A3: Cuadernos | B3: 8700
A4: Carpetas | B4: 12000
